[
  {
    "type": "function",
    "function": {
      "name": "gdal_warpreproject",
      "description": "Reprojects a raster layer to a different CRS.",
      "parameters": {
        "type": "object",
        "properties": {
          "INPUT": {
            "type": "string",
            "description": "Reprojects a raster layer to a different CRS"
          },
          "TARGET_CRS": {
            "type": "string",
            "description": "Assigns a CRS to a raster input. Defaults to EPSG:4326 if not set."
          }
        },
        "required": [
          "INPUT"
        ]
      }
    }
  },
  {
    "type": "function",
    "function": {
      "name": "native_aggregate",
      "description": "Groups features in a vector layer by a chosen expression and calculates summary values for each group using specified aggregate functions.",
      "parameters": {
        "type": "object",
        "properties": {
          "INPUT": {
            "type": "string",
            "description": "Aggregates a vector or table layer using specified summary functions."
          },
          "AGGREGATES": {
            "type": "array",
            "description": "Aggregates vector layer fields using functions like sum or mean.",
            "items": {
              "type": "string"
            }
          }
        },
        "required": [
          "INPUT",
          "AGGREGATES"
        ]
      }
    }
  },
  {
    "type": "function",
    "function": {
      "name": "native_buffer",
      "description": "Buffers vector layers to a specified distance in kilometers",
      "parameters": {
        "type": "object",
        "properties": {
          "INPUT": {
            "type": "string",
            "description": "Input vector layer to buffer"
          },
          "DISTANCE": {
            "type": "number",
            "description": "Buffer distance in kilometers. For example, 1 = 1 km, 5 = 5 km.",
            "default": 1.0
          }
        },
        "required": [
          "INPUT"
        ]
      }
    }
  },
  {
    "type": "function",
    "function": {
      "name": "native_dissolve",
      "description": "Merges features in a vector layer based on shared attributes or all features into one.",
      "parameters": {
        "type": "object",
        "properties": {
          "INPUT": {
            "type": "string",
            "description": "Dissolves features in a vector layer."
          }
        },
        "required": [
          "INPUT"
        ]
      }
    }
  },
  {
    "type": "function",
    "function": {
      "name": "native_fieldcalculator",
      "description": "Adds or updates a field in a vector layer using a formula expression per feature",
      "parameters": {
        "type": "object",
        "properties": {
          "INPUT": {
            "type": "string",
            "description": "Calculates a new or updated field in a vector layer using a formula"
          },
          "FIELD_NAME": {
            "type": "string",
            "description": "Calculates a new or updated field in a vector layer using a formula."
          },
          "FORMULA": {
            "type": "string",
            "description": "Calculates a new or updated field for each vector feature using a QGIS expression formula."
          }
        },
        "required": [
          "INPUT",
          "FIELD_NAME",
          "FORMULA"
        ]
      }
    }
  },
  {
    "type": "function",
    "function": {
      "name": "native_fixgeometries",
      "description": "Repairs invalid geometries in a vector layer.",
      "parameters": {
        "type": "object",
        "properties": {
          "INPUT": {
            "type": "string",
            "description": "Repairs invalid geometries in a vector layer."
          }
        },
        "required": [
          "INPUT"
        ]
      }
    }
  },
  {
    "type": "function",
    "function": {
      "name": "native_geometrybyexpression",
      "description": "Modifies vector layer geometries using a geometry expression.",
      "parameters": {
        "type": "object",
        "properties": {
          "INPUT": {
            "type": "string",
            "description": "Modifies the geometry of vector layer features using an expression"
          }
        },
        "required": [
          "INPUT"
        ]
      }
    }
  },
  {
    "type": "function",
    "function": {
      "name": "native_joinattributesbylocation",
      "description": "Performs a spatial join by merging attributes from one vector layer to another where features meet a spatial relationship.",
      "parameters": {
        "type": "object",
        "properties": {
          "INPUT": {
            "type": "string",
            "description": "Joins attributes from one vector layer to another based on spatial relationship"
          },
          "JOIN": {
            "type": "string",
            "description": "Joins attributes from a vector layer to another vector layer based on spatial location."
          }
        },
        "required": [
          "INPUT",
          "JOIN"
        ]
      }
    }
  },
  {
    "type": "function",
    "function": {
      "name": "native_mergevectorlayers",
      "description": "Merges multiple vector layers of the same geometry type into one layer, keeping all fields and features.",
      "parameters": {
        "type": "object",
        "properties": {
          "LAYERS": {
            "type": "array",
            "description": "Merges multiple vector layers of the same geometry type into one layer.",
            "items": {
              "type": "string"
            }
          }
        },
        "required": [
          "LAYERS"
        ]
      }
    }
  },
  {
    "type": "function",
    "function": {
      "name": "native_reprojectlayer",
      "description": "Reprojects a vector layer to another CRS.",
      "parameters": {
        "type": "object",
        "properties": {
          "INPUT": {
            "type": "string",
            "description": "Reprojects a vector layer to a different CRS"
          },
          "TARGET_CRS": {
            "type": "string",
            "description": "Reprojects a vector layer to a different CRS.",
            "default": "EPSG:4326"
          }
        },
        "required": [
          "INPUT"
        ]
      }
    }
  },
  {
    "type": "function",
    "function": {
      "name": "qgis_clip",
      "description": "Clips a vector layer using the boundaries of another vector polygon layer.",
      "parameters": {
        "type": "object",
        "properties": {
          "INPUT": {
            "type": "string",
            "description": "Clips features from a vector layer using the boundary of another vector layer."
          },
          "OVERLAY": {
            "type": "string",
            "description": "Clips a vector layer to polygons from another vector layer. Only features inside the overlay polygons are kept."
          }
        },
        "required": [
          "INPUT",
          "OVERLAY"
        ]
      }
    }
  },
  {
    "type": "function",
    "function": {
      "name": "qgis_intersection",
      "description": "Creates a new vector layer with features where the input and overlay layers intersect, combining attributes from both.",
      "parameters": {
        "type": "object",
        "properties": {
          "INPUT": {
            "type": "string",
            "description": "Intersects two vector layers and extracts overlapping features."
          },
          "OVERLAY": {
            "type": "string",
            "description": "Finds overlapping areas between two vector layers."
          }
        },
        "required": [
          "INPUT",
          "OVERLAY"
        ]
      }
    }
  },
  {
    "type": "function",
    "function": {
      "name": "qgis_joinbylocationsummary",
      "description": "Joins two vector layers by spatial relationship and adds summary statistics from the join layer to the input layer.",
      "parameters": {
        "type": "object",
        "properties": {
          "INPUT": {
            "type": "string",
            "description": "Joins vector layers by location and adds summary attributes from the join layer."
          },
          "JOIN": {
            "type": "string",
            "description": "Joins attributes from a vector layer based on spatial relationships with another vector layer."
          }
        },
        "required": [
          "INPUT",
          "JOIN"
        ]
      }
    }
  },
  {
    "type": "function",
    "function": {
      "name": "qgis_statisticsbycategories",
      "description": "Calculates grouped statistics for vector layer attributes based on unique values in specified category fields. Outputs a summary table.",
      "parameters": {
        "type": "object",
        "properties": {
          "INPUT": {
            "type": "string",
            "description": "Calculates statistics for a vector layer grouped by a category field."
          },
          "CATEGORIES_FIELD_NAME": {
            "type": "array",
            "description": "Calculates statistics for vector features grouped by values in the specified field(s)",
            "items": {
              "type": "string"
            }
          }
        },
        "required": [
          "INPUT",
          "CATEGORIES_FIELD_NAME"
        ]
      }
    }
  },
  {
    "type": "function",
    "function": {
      "name": "native_creategrid",
      "description": "Creates a regular grid of polygons (rectangles or hexagons) covering a specified extent. Useful for spatial sampling, heat maps, and aggregating point data into cells.",
      "parameters": {
        "type": "object",
        "properties": {
          "TYPE": {
            "type": "integer",
            "description": "Grid type: 0=Point, 1=Line, 2=Rectangle, 3=Diamond, 4=Hexagon. Default: 2",
            "default": 2
          },
          "EXTENT": {
            "type": "string",
            "description": "Grid extent as 'xmin,xmax,ymin,ymax [EPSG:code]'. Use a layer name to auto-detect extent."
          },
          "HSPACING": {
            "type": "number",
            "description": "Horizontal spacing between grid cells (in CRS units, e.g. degrees for EPSG:4326)",
            "default": 0.01
          },
          "VSPACING": {
            "type": "number",
            "description": "Vertical spacing between grid cells (in CRS units)",
            "default": 0.01
          },
          "CRS": {
            "type": "string",
            "description": "CRS for the output grid. Default: EPSG:4326",
            "default": "EPSG:4326"
          }
        },
        "required": [
          "EXTENT"
        ]
      }
    }
  },
  {
    "type": "function",
    "function": {
      "name": "native_zonalstatisticsfb",
      "description": "Calculates raster statistics (mean, min, max, sum, count, std dev) for each polygon zone in a vector layer. Creates a new layer with the statistics appended as columns. Use when the user wants to summarise raster values within polygons (e.g. average elevation per district, total rainfall per field).",
      "parameters": {
        "type": "object",
        "properties": {
          "INPUT": {
            "type": "string",
            "description": "Vector polygon layer defining the zones"
          },
          "INPUT_RASTER": {
            "type": "string",
            "description": "Raster layer to compute statistics from"
          },
          "RASTER_BAND": {
            "type": "integer",
            "description": "Raster band number to analyse. Default: 1",
            "default": 1
          },
          "COLUMN_PREFIX": {
            "type": "string",
            "description": "Prefix for the new statistic columns. Default: '_'",
            "default": "_"
          },
          "STATISTICS": {
            "type": "array",
            "description": "Statistics to compute: 0=Count, 1=Sum, 2=Mean, 3=Median, 4=StDev, 5=Min, 6=Max. Default: [2] (Mean)",
            "items": {
              "type": "integer"
            },
            "default": [
              2
            ]
          }
        },
        "required": [
          "INPUT",
          "INPUT_RASTER"
        ]
      }
    }
  },
  {
    "type": "function",
    "function": {
      "name": "query_rwanda_zonal_stats",
      "description": "Query agricultural zonal statistics for Rwanda. Use query_type='district_summary' (DEFAULT) for per-district NDVI/crop overviews \u2014 works for all districts, a single province, or a single district. Use query_type='ndvi_timeseries' ONLY when you have a specific h3_index or parcel_id.",
      "parameters": {
        "type": "object",
        "properties": {
          "query_type": {
            "type": "string",
            "enum": [
              "district_summary",
              "ndvi_timeseries"
            ],
            "description": "district_summary: aggregated NDVI stats per district/province (no h3_index needed, this is the default). ndvi_timeseries: weekly NDVI time-series for a SPECIFIC h3_index or parcel_id (REQUIRED, will error without one)."
          },
          "district": {
            "type": "string",
            "description": "District name to filter by (optional, for district_summary)"
          },
          "province": {
            "type": "string",
            "description": "Province name to filter by (optional, for district_summary)"
          },
          "h3_index": {
            "type": "string",
            "description": "H3 hexagon index \u2014 REQUIRED for ndvi_timeseries, not used for district_summary"
          },
          "parcel_id": {
            "type": "string",
            "description": "Parcel ID \u2014 REQUIRED for ndvi_timeseries (alternative to h3_index), not used for district_summary"
          },
          "date_from": {
            "type": "string",
            "description": "Start date in YYYY-MM-DD format (optional, for ndvi_timeseries)"
          },
          "date_to": {
            "type": "string",
            "description": "End date in YYYY-MM-DD format (optional, for ndvi_timeseries)"
          },
          "week_start": {
            "type": "string",
            "description": "Week start date in YYYY-MM-DD format (optional, for district_summary)"
          }
        },
        "required": [
          "query_type"
        ]
      }
    }
  },
  {
    "type": "function",
    "function": {
      "name": "search_satellite_imagery",
      "description": "Search for satellite imagery (Sentinel-2, Landsat) over Rwanda or a specific area. Returns available scenes with dates, cloud cover, and download links. Use this when the user asks about satellite images, remote sensing data, or wants to find imagery for a specific date/location.",
      "parameters": {
        "type": "object",
        "properties": {
          "bbox": {
            "type": "string",
            "description": "Bounding box as 'west,south,east,north' in WGS84 coordinates. Defaults to Rwanda bounds if not specified."
          },
          "datetime_range": {
            "type": "string",
            "description": "Date range in ISO 8601 format like '2024-01-01/2024-06-30'. Defaults to last 30 days."
          },
          "max_cloud_cover": {
            "type": "number",
            "description": "Maximum cloud cover percentage (0-100). Default: 20"
          },
          "limit": {
            "type": "integer",
            "description": "Maximum number of results (1-50). Default: 10"
          }
        },
        "required": []
      }
    }
  },
  {
    "type": "function",
    "function": {
      "name": "get_field_health",
      "description": "Get real-time vegetation health statistics for a specific polygon/area using Sentinel Hub. Returns NDVI (and optionally NDWI, BSI) mean/std/min/max per day for the last 30 days. PREFERRED tool when the user asks about NDVI, crop health, vegetation, or field monitoring for a specific area, buffer zone, field, or any polygon that is NOT an admin boundary. Use the geometry from an existing layer on the map (buffer, drawn polygon, uploaded field boundary). WHEN TO USE: a user-drawn polygon, any geography, optionally a specific date. WHEN NOT TO USE: Rwanda admin boundary (district/sector/cell) \u2014 use get_agri_indices. Cached weekly aggregates \u2014 use get_ndvi_stats or get_parcel_ndvi_stats.",
      "strict": false,
      "parameters": {
        "type": "object",
        "properties": {
          "geometry": {
            "type": "object",
            "description": "GeoJSON Polygon geometry of the field to analyse"
          },
          "date_from": {
            "type": "string",
            "description": "Start date ISO 8601 (default: 30 days ago)"
          },
          "date_to": {
            "type": "string",
            "description": "End date ISO 8601 (default: today)"
          },
          "index": {
            "type": "string",
            "enum": [
              "ndvi",
              "multi"
            ],
            "description": "Index type: 'ndvi' for NDVI only, 'multi' for NDVI+NDWI+BSI. Default: ndvi"
          }
        },
        "required": [
          "geometry"
        ]
      }
    }
  },
  {
    "type": "function",
    "function": {
      "name": "get_ndvi_stats",
      "description": "Read the latest NDVI vegetation index statistics for a single Rwanda district. Returns one weekly mean NDVI number. ONLY use for simple single-number NDVI lookups like 'what is the NDVI in Musanze'. Do NOT use for situation overviews, status reports, or assessment questions \u2014 use get_insurance_intelligence instead, which combines rainfall + NDVI + ET + dry spells + triggers into one report. WHEN TO USE: one weekly mean NDVI value for ONE named Rwanda district. WHEN NOT TO USE: sector/cell granularity \u2014 use get_cell_ndvi_stats. Real-time over a polygon \u2014 use get_field_health. User-uploaded field \u2014 use get_parcel_ndvi_stats.",
      "strict": false,
      "parameters": {
        "type": "object",
        "properties": {
          "district": {
            "type": "string",
            "description": "Filter results to a specific district name (e.g. Bugesera, Musanze, Gasabo)"
          }
        },
        "required": []
      }
    }
  },
  {
    "type": "function",
    "function": {
      "name": "get_cell_ndvi_stats",
      "description": "Read NDVI vegetation index statistics at sector or cell level within a district. Returns sector_name and cell_name in every row so results can be grouped by sector. When sector is provided, returns only cells in that sector. When only district is provided, returns all sectors with their cells. Use as a SUPPLEMENT after get_insurance_intelligence when the user wants spatial breakdown. Do NOT use as the primary tool for situation/overview questions. WHEN TO USE: sector- or cell-level NDVI within a named Rwanda district. WHEN NOT TO USE: district-level summary \u2014 use get_ndvi_stats. User-uploaded polygon \u2014 use get_parcel_ndvi_stats.",
      "strict": false,
      "parameters": {
        "type": "object",
        "properties": {
          "cell_name": {
            "type": "string",
            "description": "Filter by cell name (partial match supported)"
          },
          "sector": {
            "type": "string",
            "description": "Filter by sector name to see all cells within a sector"
          },
          "district": {
            "type": "string",
            "description": "Filter by district name to see all sectors and cells within a district"
          }
        },
        "required": []
      }
    }
  },
  {
    "type": "function",
    "function": {
      "name": "get_soil_properties",
      "description": "Query African soil properties at a specific location using iSDAsoil's 30m resolution machine learning predictions. Returns soil pH, nitrogen, phosphorus, potassium, organic carbon, clay/sand/silt content, texture class, and 12+ other properties. Each property includes depth (0-20cm or 20-50cm) and uncertainty estimates. Use when the user asks about soil quality, fertility, nutrients, texture, or agronomic suitability at a specific location in Africa.",
      "strict": false,
      "parameters": {
        "type": "object",
        "properties": {
          "longitude": {
            "type": "number",
            "description": "Longitude in decimal degrees (WGS84), e.g. 30.05"
          },
          "latitude": {
            "type": "number",
            "description": "Latitude in decimal degrees (WGS84), e.g. -2.30"
          },
          "properties": {
            "type": "array",
            "items": {
              "type": "string",
              "enum": [
                "ph",
                "nitrogen_total",
                "phosphorous_extractable",
                "potassium_extractable",
                "carbon_organic",
                "clay_content",
                "sand_content",
                "silt_content",
                "bulk_density",
                "cation_exchange_capacity",
                "calcium_extractable",
                "magnesium_extractable",
                "iron_extractable",
                "sulphur_extractable",
                "zinc_extractable",
                "aluminium_extractable",
                "carbon_total",
                "stone_content",
                "bedrock_depth",
                "texture_class",
                "fcc"
              ]
            },
            "description": "List of soil properties to query. Defaults to 8 most useful for agriculture: ph, nitrogen_total, phosphorous_extractable, potassium_extractable, carbon_organic, clay_content, sand_content, texture_class"
          },
          "depth": {
            "type": "string",
            "enum": [
              "0-20",
              "20-50"
            ],
            "description": "Soil depth range in centimeters. Default: 0-20"
          }
        },
        "required": [
          "longitude",
          "latitude"
        ]
      }
    }
  },
  {
    "type": "function",
    "function": {
      "name": "get_parcel_ndvi_stats",
      "description": "Read parcel-level NDVI statistics from the DuckDB cache for user-uploaded field boundaries. Updated nightly by Dagster at 10m native Sentinel-2 resolution. These are individual farm fields uploaded by users and tagged with rwanda_parcels=true. Returns per-parcel mean, std, min, max NDVI and estimated area. Use when the user asks about specific fields, farm parcels, or individual plot vegetation health. WHEN TO USE: user-uploaded field boundary by slug or name (e.g. Cyampirita, Kabarama, Kabari). WHEN NOT TO USE: Rwanda admin boundary \u2014 use get_ndvi_stats or get_cell_ndvi_stats. Real-time on an arbitrary polygon \u2014 use get_field_health.",
      "strict": false,
      "parameters": {
        "type": "object",
        "properties": {
          "parcel_name": {
            "type": "string",
            "description": "Filter by parcel/field name (partial match supported)"
          },
          "layer_id": {
            "type": "string",
            "description": "Filter by source layer ID"
          }
        },
        "required": []
      }
    }
  },
  {
    "type": "function",
    "function": {
      "name": "get_agri_indices",
      "description": "Get REAL-TIME agricultural vegetation indices for Rwanda ADMINISTRATIVE BOUNDARIES only (districts, sectors, cells). Computes 6 indices: NDVI, EVI, NDWI, SAVI, NDRE, NDBI. Only use when the user explicitly asks for district/sector/cell level analysis. Do NOT use for custom areas, buffers, fields, or drawn polygons \u2014 use get_field_health instead for those. WHEN TO USE: Rwanda ADMIN boundaries (district/sector/cell) needing live multi-index values now. WHEN NOT TO USE: user-drawn polygon \u2014 use get_field_health. Pre-aggregated weekly NDVI only \u2014 use get_ndvi_stats or get_cell_ndvi_stats.",
      "strict": false,
      "parameters": {
        "type": "object",
        "properties": {
          "admin_level": {
            "type": "string",
            "enum": [
              "district",
              "sector",
              "cell"
            ],
            "description": "Administrative level: 'district' (30 units), 'sector' (416 units, ADM3), 'cell' (2148 units, ADM4). Default: district"
          },
          "name": {
            "type": "string",
            "description": "Filter to a specific admin unit name (e.g. 'Gasabo', 'Kimisagara'). Partial match supported."
          },
          "district": {
            "type": "string",
            "description": "Filter sectors/cells within a specific district"
          },
          "date_from": {
            "type": "string",
            "description": "Start date ISO 8601 (default: 7 days ago)"
          },
          "date_to": {
            "type": "string",
            "description": "End date ISO 8601 (default: today)"
          }
        },
        "required": []
      }
    }
  },
  {
    "type": "function",
    "function": {
      "name": "add_land_cover_layer",
      "description": "Add ESRI 10m Annual LULC 2024 land cover layer to the map. Shows cropland vs non-cropland at 10m resolution from satellite imagery. Two modes: 'all' shows all 9 land cover classes (water, trees, flooded vegetation, crops, built area, bare ground, snow/ice, clouds, rangeland). 'cropland' highlights cropland in green and mutes everything else. IMPORTANT: always clip to the area of interest. Preferred: pass bbox from the relevant layer's bounds in MapState. Alternative: pass lat+lon to auto-detect the correct admin boundary. NEVER guess district names. NEVER show the entire country unless the user explicitly asks for it. WHEN TO USE: the user wants to SEE land cover on the map. WHEN NOT TO USE: numeric land-cover area or percentage for a region \u2014 use query_worldcover_stats. This tool only adds a visual layer.",
      "strict": false,
      "parameters": {
        "type": "object",
        "properties": {
          "mode": {
            "type": "string",
            "enum": [
              "all",
              "cropland"
            ],
            "description": "Visualization mode: 'all' shows all 9 land cover classes with distinct colours. 'cropland' highlights cropland areas in green and mutes all other classes. Default: all"
          },
          "lat": {
            "type": "number",
            "description": "Latitude (EPSG:4326) of the point of interest. The tool auto-detects the containing district/sector/cell from PostGIS for clipping. Use this instead of guessing district names."
          },
          "lon": {
            "type": "number",
            "description": "Longitude (EPSG:4326) of the point of interest."
          },
          "bbox": {
            "type": "array",
            "items": {
              "type": "number"
            },
            "minItems": 4,
            "maxItems": 4,
            "description": "Bounding box [west, south, east, north] in EPSG:4326 to clip the layer to. Use when the user refers to a custom area (buffer circle, drawn polygon, existing layer extent). Extract the bounds from the relevant layer in MapState."
          },
          "district": {
            "type": "string",
            "description": "Rwanda district name \u2014 only use if the user explicitly names a district. Prefer lat/lon or bbox instead."
          },
          "sector": {
            "type": "string",
            "description": "Rwanda sector name \u2014 only use if the user explicitly names a sector."
          },
          "cell": {
            "type": "string",
            "description": "Rwanda cell name \u2014 only use if the user explicitly names a cell."
          }
        },
        "required": []
      }
    }
  },
  {
    "type": "function",
    "function": {
      "name": "query_worldcover_stats",
      "description": "Query ESRI 10m LULC 2024 land-cover statistics for a specific area. Two query types: 'land_cover' returns area in hectares for each land-cover class (crops, trees, rangeland, etc.). 'largest_cropland' returns the biggest contiguous cropland plantations ranked by area. IMPORTANT: always scope to the user's area of interest. Preferred: pass bbox from the relevant layer's bounds in MapState. Alternative: pass lat+lon from the Center Point layer \u2014 the tool will auto-detect the correct admin boundary. NEVER guess district names \u2014 use bbox or lat/lon and let the tool resolve the location.",
      "strict": false,
      "parameters": {
        "type": "object",
        "properties": {
          "query_type": {
            "type": "string",
            "enum": [
              "land_cover",
              "largest_cropland"
            ],
            "description": "land_cover: area breakdown by land-cover class (DEFAULT). largest_cropland: ranked list of biggest contiguous cropland areas."
          },
          "lat": {
            "type": "number",
            "description": "Latitude (EPSG:4326) of the point of interest. The tool auto-detects the containing district/sector/cell from PostGIS. Use this instead of guessing district names."
          },
          "lon": {
            "type": "number",
            "description": "Longitude (EPSG:4326) of the point of interest."
          },
          "bbox": {
            "type": "array",
            "items": {
              "type": "number"
            },
            "minItems": 4,
            "maxItems": 4,
            "description": "Bounding box [west, south, east, north] in EPSG:4326. Use when the user refers to a custom area (buffer circle, drawn polygon, existing layer extent). Extract the bounds from the relevant layer in MapState. This performs on-the-fly analysis for the exact area."
          },
          "district": {
            "type": "string",
            "description": "Rwanda district name \u2014 only use if the user explicitly names a district. Prefer lat/lon or bbox instead."
          },
          "sector": {
            "type": "string",
            "description": "Rwanda sector name \u2014 only use if the user explicitly names a sector."
          },
          "cell": {
            "type": "string",
            "description": "Rwanda cell name \u2014 only use if the user explicitly names a cell."
          },
          "limit": {
            "type": "integer",
            "description": "Max results for largest_cropland query. Default: 10"
          }
        },
        "required": []
      }
    }
  },
  {
    "type": "function",
    "function": {
      "name": "get_crop_classifications",
      "description": "Read the latest pre-computed crop classification results from the DuckDB cache. These are generated weekly by Dagster. Returns classification labels, areas, and confidence for each district. Use ONLY when the user asks specifically about crop classification maps or land use mapping. Do NOT use when the user asks 'what about other crops' after a situation report \u2014 use get_insurance_intelligence with a different crop parameter instead. Pass lat+lon to auto-detect the correct district \u2014 NEVER guess district names. WHEN TO USE: read the most recent weekly crop classification result for parcels from the cache. WHEN NOT TO USE: classify a parcel that has not been processed yet \u2014 use identify_parcel_crop.",
      "strict": false,
      "parameters": {
        "type": "object",
        "properties": {
          "lat": {
            "type": "number",
            "description": "Latitude (EPSG:4326) of the point of interest. Auto-detects the containing district from PostGIS."
          },
          "lon": {
            "type": "number",
            "description": "Longitude (EPSG:4326) of the point of interest."
          },
          "district": {
            "type": "string",
            "description": "District name \u2014 only use if the user explicitly names a district. Prefer lat/lon instead."
          }
        },
        "required": []
      }
    }
  },
  {
    "type": "function",
    "function": {
      "name": "get_anomaly_alerts",
      "description": "Read the latest vegetation anomaly alerts. Returns locations where NDVI dropped significantly below normal, indicating crop stress, drought, or disease. Use alongside get_insurance_intelligence for situation overviews \u2014 it adds spatial hotspot detail. Also use standalone when the user asks specifically about crop problems, stress alerts, or anomalies.",
      "strict": false,
      "parameters": {
        "type": "object",
        "properties": {
          "severity": {
            "type": "string",
            "enum": [
              "high",
              "moderate"
            ],
            "description": "Filter by severity level"
          },
          "district": {
            "type": "string",
            "description": "Filter to a specific district"
          }
        },
        "required": []
      }
    }
  },
  {
    "type": "function",
    "function": {
      "name": "get_yield_risk",
      "description": "Read pre-computed yield risk assessments from the DuckDB cache. Uses Mann-Kendall trend analysis and Theil-Sen slope on NDVI time series to predict crop yield risk per district. Returns risk level (low/normal/moderate/high/critical), trend direction, and statistical confidence. Use when the user asks about harvest outlook, yield forecast, or crop risk.",
      "strict": false,
      "parameters": {
        "type": "object",
        "properties": {
          "district": {
            "type": "string",
            "description": "Filter to a specific district"
          }
        },
        "required": []
      }
    }
  },
  {
    "type": "function",
    "function": {
      "name": "get_drought_status",
      "description": "Read pre-computed drought status from the DuckDB cache. Uses Vegetation Condition Index (VCI) with NDWI water stress analysis per district. Returns drought status (normal/watch/moderate_drought/severe_drought), VCI score, and affected period count. Use when the user asks about drought, water stress, or dry conditions. WHEN TO USE: drought severity now (VCI + NDWI). WHEN NOT TO USE: forward-looking yield risk \u2014 use get_yield_risk. Recent NDVI drop alerts \u2014 use get_anomaly_alerts. Historical no-rain windows \u2014 use detect_dry_spells.",
      "strict": false,
      "parameters": {
        "type": "object",
        "properties": {
          "district": {
            "type": "string",
            "description": "Filter to a specific district"
          },
          "status": {
            "type": "string",
            "enum": [
              "severe_drought",
              "moderate_drought",
              "watch",
              "normal"
            ],
            "description": "Filter by drought status"
          }
        },
        "required": []
      }
    }
  },
  {
    "type": "function",
    "function": {
      "name": "get_crop_growth_stage",
      "description": "Read pre-computed crop growth stage analysis from the DuckDB cache. Uses NDVI phenology curve analysis to identify current crop stage per district: dormant, green_up, peak, senescence, or harvest. Returns current stage, peak NDVI date, and key phenological transition dates. Use when the user asks about crop growth, planting, harvesting, or growing season.",
      "strict": false,
      "parameters": {
        "type": "object",
        "properties": {
          "district": {
            "type": "string",
            "description": "Filter to a specific district"
          },
          "stage": {
            "type": "string",
            "enum": [
              "dormant",
              "green_up",
              "peak",
              "senescence",
              "harvest",
              "stable"
            ],
            "description": "Filter by current growth stage"
          }
        },
        "required": []
      }
    }
  },
  {
    "type": "function",
    "function": {
      "name": "get_weather_stats",
      "description": "Read daily weather statistics from the PostgreSQL cache. Data comes from Copernicus AgERA5 agrometeorological indicators at 0.1\u00b0 (~10km) grid resolution, aggregated to district level. Returns daily temperature (mean/max/min \u00b0C), precipitation (mm/day), and solar radiation (MJ/m\u00b2/day). NOTE: Results are district-level averages. Actual conditions vary within a district due to elevation, terrain, and microclimates. For location-specific weather, use get_forecast with exact lat/lon instead. Use this tool for HISTORICAL weather only.",
      "strict": false,
      "parameters": {
        "type": "object",
        "properties": {
          "district": {
            "type": "string",
            "description": "Filter to a specific district name (e.g. Bugesera, Musanze, Gasabo)"
          },
          "date_from": {
            "type": "string",
            "description": "Start date in YYYY-MM-DD format (default: 30 days ago)"
          },
          "date_to": {
            "type": "string",
            "description": "End date in YYYY-MM-DD format (default: today)"
          }
        },
        "required": []
      }
    }
  },
  {
    "type": "function",
    "function": {
      "name": "get_forecast",
      "description": "Get weather forecast for any location in Rwanda. Fuses 4 models \u2014 ECMWF IFS (9km), GFS (13km), ICON (11km), GraphCast AI (28km) \u2014 for consensus forecasts with risk assessment. Returns daily temperature, precipitation, wind, ET0, soil moisture, and a natural-language risk briefing. Each location gets unique interpolated values (sector-level precision). Use when the user asks about weather forecast, future weather, expected rainfall, upcoming conditions, or any forward-looking weather question.",
      "strict": false,
      "parameters": {
        "type": "object",
        "properties": {
          "latitude": {
            "type": "number",
            "description": "Latitude of the location (e.g. -1.9403 for Kigali)"
          },
          "longitude": {
            "type": "number",
            "description": "Longitude of the location (e.g. 29.8739 for Kigali)"
          },
          "district": {
            "type": "string",
            "description": "Rwanda district name \u2014 will use district centroid if lat/lon not provided"
          },
          "forecast_days": {
            "type": "integer",
            "description": "Number of days to forecast (1-16, default 10)"
          }
        },
        "required": []
      }
    }
  },
  {
    "type": "function",
    "function": {
      "name": "get_forecast_accuracy",
      "description": "Compare weather forecast against observed AgERA5 weather data to measure accuracy. Returns MAE (Mean Absolute Error) and bias for temperature and precipitation across districts where both forecast and observation exist. Use when the user asks about forecast accuracy, model performance, how good the forecast is, or weather prediction quality.",
      "strict": false,
      "parameters": {
        "type": "object",
        "properties": {
          "district": {
            "type": "string",
            "description": "Specific district to check accuracy for (optional \u2014 defaults to all districts)"
          },
          "lookback_days": {
            "type": "integer",
            "description": "Number of days to look back for accuracy comparison. Default: 30"
          }
        },
        "required": []
      }
    }
  },
  {
    "type": "function",
    "function": {
      "name": "get_emissions_stats",
      "description": "Read annual greenhouse gas and air pollutant emissions from the PostgreSQL cache. Data comes from EDGAR v8.0 (JRC, 0.1 degree resolution, updated annually by Dagster). Returns per-district annual emissions in tonnes for agriculture-related gases. Sectors: AGS (agricultural soils / fertilizers), ENF (enteric fermentation / livestock), MNM (manure management), AWB (agricultural waste burning). Use when the user asks about emissions, greenhouse gases, methane, CH4, N2O, CO2, NH3, fertilizer emissions, livestock emissions, or agricultural pollution for Rwanda districts.",
      "strict": false,
      "parameters": {
        "type": "object",
        "properties": {
          "district": {
            "type": "string",
            "description": "Filter to a specific district name (e.g. Musanze, Gasabo, Bugesera)"
          },
          "year": {
            "type": "integer",
            "description": "Filter to a specific year (e.g. 2022)"
          },
          "year_from": {
            "type": "integer",
            "description": "Start year for range filter (default: 5 years ago)"
          },
          "year_to": {
            "type": "integer",
            "description": "End year for range filter (default: latest available)"
          },
          "emission_type": {
            "type": "string",
            "enum": [
              "CH4",
              "N2O",
              "CO2",
              "NH3"
            ],
            "description": "Filter by gas: CH4 (methane), N2O (nitrous oxide), CO2 (carbon dioxide), NH3 (ammonia)"
          },
          "sector": {
            "type": "string",
            "enum": [
              "AGS",
              "ENF",
              "MNM",
              "AWB"
            ],
            "description": "Filter by agriculture sector: AGS (agricultural soils), ENF (enteric fermentation), MNM (manure management), AWB (agricultural waste burning)"
          }
        },
        "required": []
      }
    }
  },
  {
    "type": "function",
    "function": {
      "name": "create_management_zones",
      "description": "Create NDVI-based management zones for a field or farm polygon. Divides the area into productivity zones (Low/Medium/High) using satellite vegetation data and K-means clustering. Returns zone polygons as a map layer with NDVI statistics per zone. Use when the user asks about management zones, productivity mapping, variable-rate zones, or field zoning.",
      "strict": false,
      "parameters": {
        "type": "object",
        "properties": {
          "geometry": {
            "type": "object",
            "description": "GeoJSON Polygon geometry of the field boundary"
          },
          "num_zones": {
            "type": "integer",
            "description": "Number of zones to create (2-5, default 3)"
          },
          "date_from": {
            "type": "string",
            "description": "Start date ISO 8601 (default: 30 days ago)"
          },
          "date_to": {
            "type": "string",
            "description": "End date ISO 8601 (default: today)"
          }
        },
        "required": [
          "geometry"
        ]
      }
    }
  },
  {
    "type": "function",
    "function": {
      "name": "create_prescription_map",
      "description": "Create a variable-rate fertilizer prescription map for a field. Combines NDVI management zones with iSDAsoil data and Rwanda Agriculture Board crop-specific baseline rates. Returns zone polygons with N/P/K recommendations in kg/ha. Use when the user asks about fertilizer recommendations, prescription maps, or variable-rate application.",
      "strict": false,
      "parameters": {
        "type": "object",
        "properties": {
          "geometry": {
            "type": "object",
            "description": "GeoJSON Polygon geometry of the field boundary"
          },
          "crop_type": {
            "type": "string",
            "enum": [
              "maize",
              "beans",
              "rice",
              "wheat",
              "sorghum",
              "potato",
              "cassava"
            ],
            "description": "Crop type for baseline fertilizer rates (default: maize)"
          },
          "num_zones": {
            "type": "integer",
            "description": "Number of management zones (2-5, default 3)"
          }
        },
        "required": [
          "geometry"
        ]
      }
    }
  },
  {
    "type": "function",
    "function": {
      "name": "create_soil_sampling_plan",
      "description": "Create an optimized soil sampling plan for a field. Places 1-2 sampling points per NDVI management zone at representative locations. Returns point locations with sampling instructions and priority. Use when the user asks about soil testing, soil sampling, or where to collect soil samples.",
      "strict": false,
      "parameters": {
        "type": "object",
        "properties": {
          "geometry": {
            "type": "object",
            "description": "GeoJSON Polygon geometry of the field boundary"
          },
          "num_zones": {
            "type": "integer",
            "description": "Number of management zones for stratification (2-5, default 3)"
          }
        },
        "required": [
          "geometry"
        ]
      }
    }
  },
  {
    "type": "function",
    "function": {
      "name": "identify_parcel_crop",
      "description": "Identify what crop is growing on a field parcel using Sentinel-2 NDVI time-series and temporal signature matching. Compares the observed growth curve against known Rwanda crop profiles (maize, beans, cassava, rice, sorghum, banana, tea, coffee, potato, wheat, fallow). Returns the most likely crop with confidence score and ranked alternatives. PREFERRED tool when farmer asks 'what crop is on my field?', 'can you detect what I planted?', or 'identify the crop'. Requires a polygon geometry (field boundary). WHEN TO USE: classify ONE specific parcel right now from Sentinel-2 time-series. WHEN NOT TO USE: look up an already-classified parcel \u2014 call get_crop_classifications first (cached weekly). General 'what crops grow here' \u2014 use get_entity or search_brain.",
      "strict": false,
      "parameters": {
        "type": "object",
        "properties": {
          "geometry": {
            "type": "object",
            "description": "GeoJSON Polygon geometry of the field/parcel boundary"
          },
          "months": {
            "type": "integer",
            "description": "Number of months of NDVI history to analyze (default: 6, min: 3)"
          }
        },
        "required": [
          "geometry"
        ]
      }
    }
  },
  {
    "type": "function",
    "function": {
      "name": "confirm_crop_prediction",
      "description": "Record farmer confirmation or correction of a crop prediction. When Ingabe predicts a crop type for a parcel and the farmer says 'yes that's correct' or 'no, it's actually beans', use this tool to store the feedback as ground truth. This data improves future predictions. Use when the user confirms or corrects a crop identification result.",
      "strict": false,
      "parameters": {
        "type": "object",
        "properties": {
          "geometry": {
            "type": "object",
            "description": "GeoJSON Polygon geometry of the field/parcel"
          },
          "predicted_crop": {
            "type": "string",
            "description": "The crop that Ingabe predicted (from identify_parcel_crop result)"
          },
          "actual_crop": {
            "type": "string",
            "description": "The actual crop the farmer confirms or corrects to"
          },
          "confirmed": {
            "type": "boolean",
            "description": "true if farmer confirms prediction was correct, false if corrected"
          },
          "season": {
            "type": "string",
            "description": "Growing season (e.g. '2026A', '2026B'). Auto-detected if omitted."
          }
        },
        "required": [
          "predicted_crop",
          "actual_crop",
          "confirmed"
        ]
      }
    }
  },
  {
    "type": "function",
    "function": {
      "name": "get_soil_moisture",
      "description": "Query relative soil moisture from FAO WaPOR v3 at 100m dekadal (10-day) resolution. Returns a time series of soil moisture percentage for the given location. Use when the user asks about soil moisture, soil wetness, soil dryness, irrigation needs, or water availability in the soil. WHEN TO USE: WaPOR 100m dekadal (10-day) area-aggregated soil moisture, optical-derived. WHEN NOT TO USE: point measurement at sub-daily cadence that sees through clouds and vegetation \u2014 use get_cygnss_soil_moisture. Soil texture/chemistry \u2014 use get_soil_properties.",
      "strict": false,
      "parameters": {
        "type": "object",
        "properties": {
          "latitude": {
            "type": "number",
            "description": "Latitude in decimal degrees (WGS84)"
          },
          "longitude": {
            "type": "number",
            "description": "Longitude in decimal degrees (WGS84)"
          },
          "date_from": {
            "type": "string",
            "description": "Start date (YYYY-MM-DD). Default: 30 days ago"
          },
          "date_to": {
            "type": "string",
            "description": "End date (YYYY-MM-DD). Default: latest available"
          }
        },
        "required": [
          "latitude",
          "longitude"
        ]
      }
    }
  },
  {
    "type": "function",
    "function": {
      "name": "get_evapotranspiration",
      "description": "Query actual evapotranspiration (ET) and optionally transpiration and net primary productivity from FAO WaPOR v3 at 100m dekadal (10-day) resolution. Returns a time series of ET values in mm/day for the given location. Use when the user asks about evapotranspiration, water use, crop water consumption, water productivity, ET, or how much water a crop/field is using.",
      "strict": false,
      "parameters": {
        "type": "object",
        "properties": {
          "latitude": {
            "type": "number",
            "description": "Latitude in decimal degrees (WGS84)"
          },
          "longitude": {
            "type": "number",
            "description": "Longitude in decimal degrees (WGS84)"
          },
          "date_from": {
            "type": "string",
            "description": "Start date (YYYY-MM-DD). Default: 30 days ago"
          },
          "date_to": {
            "type": "string",
            "description": "End date (YYYY-MM-DD). Default: latest available"
          },
          "include_components": {
            "type": "boolean",
            "description": "If true, also return transpiration and net primary productivity. Default: false"
          }
        },
        "required": [
          "latitude",
          "longitude"
        ]
      }
    }
  },
  {
    "type": "function",
    "function": {
      "name": "get_food_security_alerts",
      "description": "Query IPC food security classifications for Rwanda from FEWS NET. Returns the current IPC phase (1-5 scale: 1=Minimal, 2=Stressed, 3=Crisis, 4=Emergency, 5=Famine) and any areas of concern. Use when the user asks about food security, hunger, famine risk, IPC classification, food crisis, or food insecurity in Rwanda.",
      "strict": false,
      "parameters": {
        "type": "object",
        "properties": {
          "district": {
            "type": "string",
            "description": "Optional district name to filter (e.g. Kayonza, Bugesera)"
          },
          "period": {
            "type": "string",
            "enum": [
              "current",
              "projected"
            ],
            "description": "current = latest observed situation, projected = near-term outlook. Default: current"
          }
        },
        "required": []
      }
    }
  },
  {
    "type": "function",
    "function": {
      "name": "detect_dry_spells",
      "description": "Detect historical dry spells from observed weather data (AgERA5). Scans for consecutive days where precipitation was below a threshold. Use when the user asks about dry spells, drought events, consecutive dry days, rainfall gaps, or historical drought periods for Rwanda districts.",
      "strict": false,
      "parameters": {
        "type": "object",
        "properties": {
          "district": {
            "type": "string",
            "description": "District name to filter (e.g. Gasabo, Bugesera). Optional \u2014 defaults to all districts"
          },
          "date_from": {
            "type": "string",
            "description": "Start date (YYYY-MM-DD). Default: 180 days ago"
          },
          "date_to": {
            "type": "string",
            "description": "End date (YYYY-MM-DD). Default: latest available"
          },
          "threshold_mm": {
            "type": "number",
            "description": "Daily precipitation threshold in mm \u2014 days below this count as dry. Default: 2.0"
          },
          "min_duration_days": {
            "type": "integer",
            "description": "Minimum consecutive dry days to qualify as a dry spell. Default: 10"
          }
        },
        "required": []
      }
    }
  },
  {
    "type": "function",
    "function": {
      "name": "get_insurance_accuracy",
      "description": "Compute weather data accuracy for agricultural insurance underwriting. Returns binary rainfall detection metrics (POD, FAR, HSS, CSI), dry spell detection results, NDVI-weather concordance, and an overall confidence rating (0-100). Use when the user asks about insurance accuracy, weather data reliability, rainfall detection quality, underwriting confidence, or whether weather data is good enough for crop insurance.",
      "strict": false,
      "parameters": {
        "type": "object",
        "properties": {
          "district": {
            "type": "string",
            "description": "District name (e.g. Gasabo, Bugesera). Optional \u2014 defaults to all districts"
          },
          "season": {
            "type": "string",
            "enum": [
              "A",
              "B"
            ],
            "description": "Rwanda growing season: A (Sep-Jan) or B (Feb-Jun). Optional \u2014 defaults to last 90 days"
          },
          "threshold_mm": {
            "type": "number",
            "description": "Rainfall threshold in mm for binary rain/no-rain classification. Default: 5.0"
          }
        },
        "required": []
      }
    }
  },
  {
    "type": "function",
    "function": {
      "name": "get_insurance_intelligence",
      "description": "Get a comprehensive agricultural situation report for any location in Rwanda. This is the PRIMARY tool for any question about the 'situation', 'status', 'overview', 'how is [place] doing', or 'what's happening in [place]'. Combines rainfall (CHIRPS cumulative + SPI drought index), vegetation health (NDVI + Sentinel-1 SAR), evapotranspiration (WaPOR), soil moisture, dry spells, season progress, parametric trigger thresholds, and multi-model forecast outlook (ECMWF IFS + GFS + ICON + GraphCast) into one unified report. Reports are location-based (not crop-specific) \u2014 they show weather and vegetation conditions for the area regardless of what is planted. Supports 4 audience views: farmer (simple), insurance (trigger table), agronomist (technical + recommendations), scientist (full methodology). Works at any admin level: district, sector, cell, or village. COMPARISON MODE: when the user asks to compare areas (e.g. 'compare sectors in Nyamasheke', 'which districts get more rain', 'difference between sectors'), set compare_level to the level being compared. This returns ALL signals for every child area in one call. IMPORTANT: at least one location parameter (district, sector, cell, or village) is required. WHEN TO USE: open-ended 'what is happening here' / 'how is this farm doing' over a Rwanda location \u2014 fuses NDVI + weather + drought + crop into one report. WHEN NOT TO USE: the user asked one narrow question (just rainfall, just NDVI, just soil) \u2014 call the specific tool. Do NOT default to this for every Rwanda question.",
      "strict": false,
      "parameters": {
        "type": "object",
        "properties": {
          "crop": {
            "type": "string",
            "description": "Optional crop name if the user explicitly mentions one. The report shows location-based conditions (rainfall, NDVI, soil moisture, etc) regardless \u2014 we cannot detect what crop is planted from satellite. Leave empty or omit for general location reports."
          },
          "season": {
            "type": "string",
            "enum": [
              "A",
              "B"
            ],
            "description": "Growing season: A (Sep-Feb) or B (Feb-Jul). Auto-detected if omitted"
          },
          "district": {
            "type": "string",
            "description": "District name (e.g. Musanze, Gasabo, Bugesera)"
          },
          "sector": {
            "type": "string",
            "description": "Sector name within a district (e.g. Kinigi, Kimironko)"
          },
          "cell": {
            "type": "string",
            "description": "Cell name within a sector"
          },
          "village": {
            "type": "string",
            "description": "Village name \u2014 most specific admin level"
          },
          "audience": {
            "type": "string",
            "enum": [
              "farmer",
              "insurance",
              "agronomist",
              "scientist"
            ],
            "description": "Who is reading this report. Default: farmer"
          },
          "compare_level": {
            "type": "string",
            "enum": [
              "district",
              "sector",
              "cell"
            ],
            "description": "COMPARISON MODE: set this to compare all child areas at this admin level. 'sector' with district=X compares all sectors in district X. 'cell' with sector=Y compares all cells in sector Y. 'district' compares all 30 districts nationwide. Returns rainfall, SPI, NDVI, soil moisture, ET, temperature, SAR, and dry spells for every area. Only set this when the user asks to COMPARE areas \u2014 omit for single-location reports."
          }
        },
        "required": []
      }
    }
  },
  {
    "type": "function",
    "function": {
      "name": "predict_ndvi_from_sar",
      "description": "Predict NDVI vegetation index from Sentinel-1 SAR radar data when optical imagery is blocked by clouds. Uses 30-day SAR backscatter trajectory to estimate what NDVI would be. Use when the user asks about crop health during cloudy periods or wants cloud-proof monitoring.",
      "parameters": {
        "type": "object",
        "properties": {
          "bbox": {
            "type": "string",
            "description": "Bounding box as 'lon_min,lat_min,lon_max,lat_max'"
          },
          "target_date": {
            "type": "string",
            "description": "Date to predict NDVI for (YYYY-MM-DD). Default: today"
          }
        },
        "required": [
          "bbox"
        ]
      }
    }
  },
  {
    "type": "function",
    "function": {
      "name": "detect_water_bodies",
      "description": "Detect water bodies and ponds from Sentinel-1 SAR radar imagery. Works through clouds and under tree canopy. Use for aquaculture pond verification, water body monitoring, or checking if ponds are filled. Returns water area in hectares and water body polygons.",
      "parameters": {
        "type": "object",
        "properties": {
          "bbox": {
            "type": "string",
            "description": "Bounding box as 'lon_min,lat_min,lon_max,lat_max'"
          },
          "date": {
            "type": "string",
            "description": "Target date (YYYY-MM-DD). Default: most recent S1 pass"
          }
        },
        "required": [
          "bbox"
        ]
      }
    }
  },
  {
    "type": "function",
    "function": {
      "name": "detect_flood_extent",
      "description": "Delineate flood extent by comparing Sentinel-1 SAR radar imagery from before and after a flood event. Returns new flood area (excluding permanent water bodies) with polygons suitable for insurance claim validation.",
      "parameters": {
        "type": "object",
        "properties": {
          "bbox": {
            "type": "string",
            "description": "Bounding box as 'lon_min,lat_min,lon_max,lat_max'"
          },
          "date_before": {
            "type": "string",
            "description": "Pre-flood date (YYYY-MM-DD)"
          },
          "date_after": {
            "type": "string",
            "description": "Post-flood date (YYYY-MM-DD)"
          }
        },
        "required": [
          "bbox",
          "date_before",
          "date_after"
        ]
      }
    }
  },
  {
    "type": "function",
    "function": {
      "name": "get_alos_l_band_stats",
      "description": "Get ALOS-2 PALSAR-2 L-band (24cm wavelength) SAR backscatter statistics for a bounding box over one or more years. Returns per-year HH/HV gamma-naught stats plus the HH/HV ratio in dB. The HH/HV ratio discriminates vegetation structure: forest <-5dB, crops -5 to -10dB, bare/water >-3dB. L-band penetrates dense canopy where Sentinel-1 C-band saturates. Use for crop-type discrimination, biomass analysis, or deep canopy monitoring. No auth needed (Digital Earth Africa public bucket).",
      "parameters": {
        "type": "object",
        "properties": {
          "bbox": {
            "type": "string",
            "description": "Bounding box as 'lon_min,lat_min,lon_max,lat_max'"
          },
          "years": {
            "type": "string",
            "description": "Comma-separated years to analyse (e.g. '2020,2021,2022'). Available: 2015-2022 (PALSAR-2), 2007-2010 (PALSAR). Default: 2020,2021,2022"
          }
        },
        "required": [
          "bbox"
        ]
      }
    }
  },
  {
    "type": "function",
    "function": {
      "name": "get_alos_temporal_variation",
      "description": "Compute year-over-year variation in ALOS PALSAR L-band HH/HV ratio across multiple years. Reveals agricultural activity patterns: stable ratio = perennial crops/forest, variable ratio = annual crop rotation, high HV std = heterogeneous smallholder mosaics. Use for long-term land-use change analysis or distinguishing perennial vs annual cropping systems.",
      "parameters": {
        "type": "object",
        "properties": {
          "bbox": {
            "type": "string",
            "description": "Bounding box as 'lon_min,lat_min,lon_max,lat_max'"
          },
          "years": {
            "type": "string",
            "description": "Comma-separated years (need at least 2). Default: 2018,2019,2020,2021,2022"
          }
        },
        "required": [
          "bbox"
        ]
      }
    }
  },
  {
    "type": "function",
    "function": {
      "name": "check_cygnss_availability",
      "description": "Check what NASA CYGNSS (GNSS-Reflectometry) data is available for a bounding box. CYGNSS is an 8-satellite constellation that measures GPS signal reflections to detect soil moisture and surface water. Coverage \u00b138\u00b0 latitude (Rwanda is dead center), median 3-hour revisit, ~6-day latency. CYGNSS's killer feature: L-band penetrates vegetation canopy, detecting water UNDER trees where Sentinel-1 and optical fail. Returns granule counts, latest dates, and auth status. No auth needed for this diagnostic tool. Use first before calling get_cygnss_soil_moisture or get_cygnss_watermask.",
      "parameters": {
        "type": "object",
        "properties": {
          "bbox": {
            "type": "string",
            "description": "Bounding box as 'lon_min,lat_min,lon_max,lat_max'. Default: Rwanda national bbox."
          }
        },
        "required": []
      }
    }
  },
  {
    "type": "function",
    "function": {
      "name": "get_cygnss_soil_moisture",
      "description": "Get CYGNSS soil moisture timeseries for a point (lat/lon). Returns volumetric water content (m\u00b3/m\u00b3, 0-5cm depth) at 9km or 36km resolution. Interpretation: <0.10 dry, 0.10-0.25 moist, 0.25-0.40 wet/flood risk, >0.40 likely standing water. Complements WaPOR (100m dekadal) with higher temporal resolution. Requires NASA Earthdata credentials \u2014 if unavailable, returns granule availability without data. Use for drought monitoring, irrigation planning, or flood risk at a specific field.",
      "parameters": {
        "type": "object",
        "properties": {
          "lat": {
            "type": "number",
            "description": "Latitude in decimal degrees (Rwanda: -2.84 to -1.05)"
          },
          "lon": {
            "type": "number",
            "description": "Longitude in decimal degrees (Rwanda: 28.86 to 30.90)"
          },
          "days_back": {
            "type": "integer",
            "description": "How many days of history to pull. Default: 90"
          },
          "resolution_km": {
            "type": "integer",
            "description": "Grid resolution, 9 or 36 km. Default: 9"
          }
        },
        "required": [
          "lat",
          "lon"
        ]
      }
    }
  },
  {
    "type": "function",
    "function": {
      "name": "get_cygnss_watermask",
      "description": "Get CYGNSS binary water/land classification at ~1km resolution for a bounding box. L-band GNSS-R detects water under vegetation canopy \u2014 ponds hidden under banana groves show up here where Sentinel-1 fails. Coarser than SAR water detection (detect_water_bodies at ~10m) but sees through canopy. Use for aquaculture pond verification under forest cover, or cross-validating Sentinel-1 flood extent. Requires NASA Earthdata credentials.",
      "parameters": {
        "type": "object",
        "properties": {
          "bbox": {
            "type": "string",
            "description": "Bounding box as 'lon_min,lat_min,lon_max,lat_max'"
          },
          "date": {
            "type": "string",
            "description": "Target date (YYYY-MM-DD). Default: 7 days ago (accounting for 6-day latency)"
          },
          "product": {
            "type": "string",
            "description": "'watermask_daily' (1km, daily) or 'watermask_monthly' (1km, monthly). Default: watermask_daily"
          }
        },
        "required": [
          "bbox"
        ]
      }
    }
  },
  {
    "type": "function",
    "function": {
      "name": "search_brain",
      "description": "Search the knowledge brain for entities and information. Uses hybrid search (keyword + vector) across brain pages. Returns ranked results with compiled truth summaries. Use when the user asks about a field, farmer, district, claim, policy, or any entity the brain might know about.",
      "parameters": {
        "type": "object",
        "properties": {
          "query": {
            "type": "string",
            "description": "Natural language search query"
          },
          "type": {
            "type": "string",
            "description": "Filter by page type: field, farmer, district, company, insurance_worker, claim, policy, season, crop, weather_station, equipment"
          },
          "limit": {
            "type": "integer",
            "description": "Max results to return (default 10, max 100)"
          }
        },
        "required": [
          "query"
        ]
      }
    }
  },
  {
    "type": "function",
    "function": {
      "name": "get_entity",
      "description": "Get a specific brain page by its slug. Returns the full compiled truth, recent timeline entries, tags, and linked entities. Use when the user asks about a specific known entity like 'field-gasabo-001' or 'farmer-uwimana'.",
      "parameters": {
        "type": "object",
        "properties": {
          "slug": {
            "type": "string",
            "description": "The entity slug (e.g. 'field-gasabo-001', 'farmer-uwimana')"
          }
        },
        "required": [
          "slug"
        ]
      }
    }
  },
  {
    "type": "function",
    "function": {
      "name": "add_observation",
      "description": "Add a timeline observation to a brain page. Use when the user reports a field visit, observation, measurement, or event that should be recorded in an entity's history. The brain grows with every observation.",
      "parameters": {
        "type": "object",
        "properties": {
          "slug": {
            "type": "string",
            "description": "The entity slug to add the observation to"
          },
          "summary": {
            "type": "string",
            "description": "Short summary of the observation"
          },
          "detail": {
            "type": "string",
            "description": "Detailed description (optional)"
          },
          "date": {
            "type": "string",
            "description": "Date of the observation (YYYY-MM-DD). Default: today"
          },
          "source": {
            "type": "string",
            "description": "Source of the observation (e.g. 'field_visit', 'satellite', 'user_report'). Default: 'user_report'"
          }
        },
        "required": [
          "slug",
          "summary"
        ]
      }
    }
  },
  {
    "type": "function",
    "function": {
      "name": "search_location",
      "description": "Search for a location by name and return its bounding box and coordinates. Use this when the user mentions a place name and you need geographic coordinates for satellite imagery or spectral index tools.",
      "strict": true,
      "parameters": {
        "type": "object",
        "properties": {
          "query": {
            "type": "string",
            "description": "Place name to search for, e.g. 'Musanze district, Rwanda' or 'Kigali'"
          }
        },
        "required": [
          "query"
        ],
        "additionalProperties": false
      }
    }
  },
  {
    "type": "function",
    "function": {
      "name": "display_satellite_layer",
      "description": "Display satellite imagery (true color) on the map for a specific area and date range. Searches Earth Search for the best Sentinel-2 scene and adds it as a visible tile layer. Use this when the user wants to SEE satellite imagery on the map for a location.",
      "strict": true,
      "parameters": {
        "type": "object",
        "properties": {
          "bbox": {
            "type": "string",
            "description": "Bounding box as 'west,south,east,north' in WGS84 coordinates, e.g. '29.44,-1.72,29.68,-1.50'"
          },
          "date_from": {
            "type": "string",
            "description": "Start date in ISO 8601 format, e.g. '2025-01-01'"
          },
          "date_to": {
            "type": "string",
            "description": "End date in ISO 8601 format, e.g. '2025-01-31'"
          },
          "layer_name": {
            "type": "string",
            "description": "Display name for the map layer, e.g. 'Musanze TCI Jan 2025'"
          }
        },
        "required": [
          "bbox",
          "date_from",
          "date_to",
          "layer_name"
        ],
        "additionalProperties": false
      }
    }
  },
  {
    "type": "function",
    "function": {
      "name": "compute_spectral_index",
      "description": "Compute a spectral index (NDVI, NDWI, or NBR) over an area and display it on the map with a colormap. Returns area statistics (mean, std, min, max). Use this for vegetation health analysis (NDVI), water/flood detection (NDWI), or burn severity mapping (NBR). Always call search_location first to get the bbox. WHEN TO USE: the user wants to SEE NDVI/NDWI/NBR as a coloured layer on the map. WHEN NOT TO USE: numbers/stats only \u2014 use get_field_health or get_ndvi_stats. This tool renders; it does not return tabular metrics.",
      "strict": true,
      "parameters": {
        "type": "object",
        "properties": {
          "bbox": {
            "type": "string",
            "description": "Bounding box as 'west,south,east,north' in WGS84 coordinates"
          },
          "index": {
            "type": "string",
            "enum": [
              "ndvi",
              "ndwi",
              "nbr"
            ],
            "description": "Spectral index to compute: 'ndvi' (vegetation health), 'ndwi' (water/flooding), or 'nbr' (burn severity)"
          },
          "date_from": {
            "type": "string",
            "description": "Start date in ISO 8601 format, e.g. '2025-01-01'"
          },
          "date_to": {
            "type": "string",
            "description": "End date in ISO 8601 format, e.g. '2025-01-31'"
          },
          "layer_name": {
            "type": "string",
            "description": "Display name for the map layer, e.g. 'NDVI Musanze Jan 2025'"
          }
        },
        "required": [
          "bbox",
          "index",
          "date_from",
          "date_to",
          "layer_name"
        ],
        "additionalProperties": false
      }
    }
  }
]
